{
  "id": "d5cfc49a-af4b-4912-81b5-9b9f56006759",
  "prevId": "00000000-0000-0000-0000-000000000000",
  "version": "7",
  "dialect": "postgresql",
  "tables": {
    "public.events": {
      "name": "events",
      "schema": "",
      "columns": {
        "id": {
          "name": "id",
          "type": "uuid",
          "primaryKey": true,
          "notNull": true,
          "default": "gen_random_uuid()"
        },
        "user_id": {
          "name": "user_id",
          "type": "uuid",
          "primaryKey": false,
          "notNull": false
        },
        "group_name": {
          "name": "group_name",
          "type": "varchar(100)",
          "primaryKey": false,
          "notNull": true
        },
        "expected_members": {
          "name": "expected_members",
          "type": "varchar(20)",
          "primaryKey": false,
          "notNull": false
        },
        "preferred_location": {
          "name": "preferred_location",
          "type": "varchar(100)",
          "primaryKey": false,
          "notNull": false
        },
        "budget_range": {
          "name": "budget_range",
          "type": "varchar(50)",
          "primaryKey": false,
          "notNull": false
        },
        "survey_url": {
          "name": "survey_url",
          "type": "varchar(255)",
          "primaryKey": false,
          "notNull": false
        },
        "status": {
          "name": "status",
          "type": "varchar(20)",
          "primaryKey": false,
          "notNull": true,
          "default": "'collecting'"
        },
        "letter_unlock_at": {
          "name": "letter_unlock_at",
          "type": "timestamp",
          "primaryKey": false,
          "notNull": false
        },
        "letter_unlocked": {
          "name": "letter_unlocked",
          "type": "boolean",
          "primaryKey": false,
          "notNull": true,
          "default": false
        },
        "selected_restaurant_id": {
          "name": "selected_restaurant_id",
          "type": "uuid",
          "primaryKey": false,
          "notNull": false
        },
        "meeting_date": {
          "name": "meeting_date",
          "type": "timestamp",
          "primaryKey": false,
          "notNull": false
        },
        "meeting_time": {
          "name": "meeting_time",
          "type": "varchar(10)",
          "primaryKey": false,
          "notNull": false
        },
        "additional_message": {
          "name": "additional_message",
          "type": "text",
          "primaryKey": false,
          "notNull": false
        },
        "created_at": {
          "name": "created_at",
          "type": "timestamp",
          "primaryKey": false,
          "notNull": true,
          "default": "now()"
        },
        "updated_at": {
          "name": "updated_at",
          "type": "timestamp",
          "primaryKey": false,
          "notNull": true,
          "default": "now()"
        }
      },
      "indexes": {},
      "foreignKeys": {
        "events_user_id_users_id_fk": {
          "name": "events_user_id_users_id_fk",
          "tableFrom": "events",
          "tableTo": "users",
          "columnsFrom": [
            "user_id"
          ],
          "columnsTo": [
            "id"
          ],
          "onDelete": "no action",
          "onUpdate": "no action"
        }
      },
      "compositePrimaryKeys": {},
      "uniqueConstraints": {
        "events_survey_url_unique": {
          "name": "events_survey_url_unique",
          "nullsNotDistinct": false,
          "columns": [
            "survey_url"
          ]
        }
      },
      "policies": {},
      "checkConstraints": {},
      "isRLSEnabled": false
    },
    "public.letters": {
      "name": "letters",
      "schema": "",
      "columns": {
        "id": {
          "name": "id",
          "type": "uuid",
          "primaryKey": true,
          "notNull": true,
          "default": "gen_random_uuid()"
        },
        "event_id": {
          "name": "event_id",
          "type": "uuid",
          "primaryKey": false,
          "notNull": true
        },
        "survey_response_id": {
          "name": "survey_response_id",
          "type": "uuid",
          "primaryKey": false,
          "notNull": false
        },
        "guest_name": {
          "name": "guest_name",
          "type": "varchar(100)",
          "primaryKey": false,
          "notNull": true
        },
        "content": {
          "name": "content",
          "type": "text",
          "primaryKey": false,
          "notNull": false
        },
        "stickers": {
          "name": "stickers",
          "type": "jsonb",
          "primaryKey": false,
          "notNull": false
        },
        "is_read": {
          "name": "is_read",
          "type": "boolean",
          "primaryKey": false,
          "notNull": true,
          "default": false
        },
        "created_at": {
          "name": "created_at",
          "type": "timestamp",
          "primaryKey": false,
          "notNull": true,
          "default": "now()"
        }
      },
      "indexes": {},
      "foreignKeys": {
        "letters_event_id_events_id_fk": {
          "name": "letters_event_id_events_id_fk",
          "tableFrom": "letters",
          "tableTo": "events",
          "columnsFrom": [
            "event_id"
          ],
          "columnsTo": [
            "id"
          ],
          "onDelete": "cascade",
          "onUpdate": "no action"
        },
        "letters_survey_response_id_survey_responses_id_fk": {
          "name": "letters_survey_response_id_survey_responses_id_fk",
          "tableFrom": "letters",
          "tableTo": "survey_responses",
          "columnsFrom": [
            "survey_response_id"
          ],
          "columnsTo": [
            "id"
          ],
          "onDelete": "no action",
          "onUpdate": "no action"
        }
      },
      "compositePrimaryKeys": {},
      "uniqueConstraints": {},
      "policies": {},
      "checkConstraints": {},
      "isRLSEnabled": false
    },
    "public.payment_requests": {
      "name": "payment_requests",
      "schema": "",
      "columns": {
        "id": {
          "name": "id",
          "type": "uuid",
          "primaryKey": true,
          "notNull": true,
          "default": "gen_random_uuid()"
        },
        "event_id": {
          "name": "event_id",
          "type": "uuid",
          "primaryKey": false,
          "notNull": true
        },
        "status": {
          "name": "status",
          "type": "varchar(20)",
          "primaryKey": false,
          "notNull": true,
          "default": "'pending'"
        },
        "requested_at": {
          "name": "requested_at",
          "type": "timestamp",
          "primaryKey": false,
          "notNull": true,
          "default": "now()"
        },
        "approved_at": {
          "name": "approved_at",
          "type": "timestamp",
          "primaryKey": false,
          "notNull": false
        },
        "approved_by": {
          "name": "approved_by",
          "type": "uuid",
          "primaryKey": false,
          "notNull": false
        }
      },
      "indexes": {},
      "foreignKeys": {
        "payment_requests_event_id_events_id_fk": {
          "name": "payment_requests_event_id_events_id_fk",
          "tableFrom": "payment_requests",
          "tableTo": "events",
          "columnsFrom": [
            "event_id"
          ],
          "columnsTo": [
            "id"
          ],
          "onDelete": "cascade",
          "onUpdate": "no action"
        },
        "payment_requests_approved_by_users_id_fk": {
          "name": "payment_requests_approved_by_users_id_fk",
          "tableFrom": "payment_requests",
          "tableTo": "users",
          "columnsFrom": [
            "approved_by"
          ],
          "columnsTo": [
            "id"
          ],
          "onDelete": "no action",
          "onUpdate": "no action"
        }
      },
      "compositePrimaryKeys": {},
      "uniqueConstraints": {},
      "policies": {},
      "checkConstraints": {},
      "isRLSEnabled": false
    },
    "public.restaurant_recommendations": {
      "name": "restaurant_recommendations",
      "schema": "",
      "columns": {
        "id": {
          "name": "id",
          "type": "uuid",
          "primaryKey": true,
          "notNull": true,
          "default": "gen_random_uuid()"
        },
        "event_id": {
          "name": "event_id",
          "type": "uuid",
          "primaryKey": false,
          "notNull": true
        },
        "name": {
          "name": "name",
          "type": "varchar(100)",
          "primaryKey": false,
          "notNull": true
        },
        "category": {
          "name": "category",
          "type": "varchar(50)",
          "primaryKey": false,
          "notNull": false
        },
        "location": {
          "name": "location",
          "type": "varchar(255)",
          "primaryKey": false,
          "notNull": false
        },
        "price_range": {
          "name": "price_range",
          "type": "varchar(50)",
          "primaryKey": false,
          "notNull": false
        },
        "image_url": {
          "name": "image_url",
          "type": "varchar(500)",
          "primaryKey": false,
          "notNull": false
        },
        "match_score": {
          "name": "match_score",
          "type": "integer",
          "primaryKey": false,
          "notNull": false
        },
        "match_reasons": {
          "name": "match_reasons",
          "type": "jsonb",
          "primaryKey": false,
          "notNull": false
        },
        "created_at": {
          "name": "created_at",
          "type": "timestamp",
          "primaryKey": false,
          "notNull": true,
          "default": "now()"
        }
      },
      "indexes": {},
      "foreignKeys": {
        "restaurant_recommendations_event_id_events_id_fk": {
          "name": "restaurant_recommendations_event_id_events_id_fk",
          "tableFrom": "restaurant_recommendations",
          "tableTo": "events",
          "columnsFrom": [
            "event_id"
          ],
          "columnsTo": [
            "id"
          ],
          "onDelete": "cascade",
          "onUpdate": "no action"
        }
      },
      "compositePrimaryKeys": {},
      "uniqueConstraints": {},
      "policies": {},
      "checkConstraints": {},
      "isRLSEnabled": false
    },
    "public.survey_responses": {
      "name": "survey_responses",
      "schema": "",
      "columns": {
        "id": {
          "name": "id",
          "type": "uuid",
          "primaryKey": true,
          "notNull": true,
          "default": "gen_random_uuid()"
        },
        "event_id": {
          "name": "event_id",
          "type": "uuid",
          "primaryKey": false,
          "notNull": true
        },
        "guest_name": {
          "name": "guest_name",
          "type": "varchar(100)",
          "primaryKey": false,
          "notNull": true
        },
        "food_types": {
          "name": "food_types",
          "type": "jsonb",
          "primaryKey": false,
          "notNull": false
        },
        "atmospheres": {
          "name": "atmospheres",
          "type": "jsonb",
          "primaryKey": false,
          "notNull": false
        },
        "price_range": {
          "name": "price_range",
          "type": "varchar(50)",
          "primaryKey": false,
          "notNull": false
        },
        "dietary_restriction": {
          "name": "dietary_restriction",
          "type": "varchar(50)",
          "primaryKey": false,
          "notNull": false
        },
        "allergy_info": {
          "name": "allergy_info",
          "type": "varchar(255)",
          "primaryKey": false,
          "notNull": false
        },
        "disliked_foods": {
          "name": "disliked_foods",
          "type": "text",
          "primaryKey": false,
          "notNull": false
        },
        "preferred_location": {
          "name": "preferred_location",
          "type": "varchar(100)",
          "primaryKey": false,
          "notNull": false
        },
        "created_at": {
          "name": "created_at",
          "type": "timestamp",
          "primaryKey": false,
          "notNull": true,
          "default": "now()"
        }
      },
      "indexes": {},
      "foreignKeys": {
        "survey_responses_event_id_events_id_fk": {
          "name": "survey_responses_event_id_events_id_fk",
          "tableFrom": "survey_responses",
          "tableTo": "events",
          "columnsFrom": [
            "event_id"
          ],
          "columnsTo": [
            "id"
          ],
          "onDelete": "cascade",
          "onUpdate": "no action"
        }
      },
      "compositePrimaryKeys": {},
      "uniqueConstraints": {},
      "policies": {},
      "checkConstraints": {},
      "isRLSEnabled": false
    },
    "public.users": {
      "name": "users",
      "schema": "",
      "columns": {
        "id": {
          "name": "id",
          "type": "uuid",
          "primaryKey": true,
          "notNull": true,
          "default": "gen_random_uuid()"
        },
        "email": {
          "name": "email",
          "type": "varchar(255)",
          "primaryKey": false,
          "notNull": true
        },
        "name": {
          "name": "name",
          "type": "varchar(100)",
          "primaryKey": false,
          "notNull": false
        },
        "created_at": {
          "name": "created_at",
          "type": "timestamp",
          "primaryKey": false,
          "notNull": true,
          "default": "now()"
        }
      },
      "indexes": {},
      "foreignKeys": {},
      "compositePrimaryKeys": {},
      "uniqueConstraints": {
        "users_email_unique": {
          "name": "users_email_unique",
          "nullsNotDistinct": false,
          "columns": [
            "email"
          ]
        }
      },
      "policies": {},
      "checkConstraints": {},
      "isRLSEnabled": false
    }
  },
  "enums": {},
  "schemas": {},
  "sequences": {},
  "roles": {},
  "policies": {},
  "views": {},
  "_meta": {
    "columns": {},
    "schemas": {},
    "tables": {}
  }
}